priori/__init__.py
priori/priori.py
priori/data/__init__.py
priori/data/primary_intx_regulon.pkl
priori/features/__init__.py
priori/features/expression_utils.py
priori/regulon/__init__.py
priori/regulon/regulon_enrichment.py
priori/regulon/regulon_utils.py
priori_regulon_enrichment-1.0.6.dist-info/LICENSE
priori_regulon_enrichment-1.0.6.dist-info/METADATA
priori_regulon_enrichment-1.0.6.dist-info/WHEEL
priori_regulon_enrichment-1.0.6.dist-info/entry_points.txt
priori_regulon_enrichment-1.0.6.dist-info/top_level.txt
priori_regulon_enrichment-1.0.6.dist-info/RECORD
