Metadata-Version: 2.1
Name: priori-regulon-enrichment
Version: 1.0.6
Summary: Priori predicts transcription factor activity from RNA sequencing data using prior, literature-supported regulatory relationship information.
Home-page: https://github.com/ohsu-comp-bio/regulon-enrichment
Author: Joseph Estabrook, William Yashar, & Emek Demir
Author-email: yashar@ohsu.edu
Classifier: Programming Language :: Python :: 3
Classifier: License :: OSI Approved :: GNU General Public License v3 (GPLv3)
Classifier: Operating System :: OS Independent
License-File: LICENSE
Requires-Dist: numpy >=1.19.5
Requires-Dist: pandas >=1.1.5
Requires-Dist: scikit-learn >=0.23.2
Requires-Dist: scipy >=1.5.3
Requires-Dist: tqdm >=4.64.0
Requires-Dist: dill >=0.3.5.1
Requires-Dist: statsmodels >=0.12.2
